Metadata-Version: 1.0
Name: scriptcraft
Version: 0.1.27
Summary: Scriptcraft programming game - program your units to fight against other players.
Home-page: http://github.com/krzysiumed/scriptcraft
Author: Krzysztof Medrela
Author-email: krzysiumed@gmail.com
License: GPLv3
Keywords: scriptcraft,programming game,game
Platform: UNKNOWN
Classifier: License :: OSI Approved :: GNU General Public License v3 or later (GPLv3+)
Classifier: Natural Language :: Polish
Classifier: Operating System :: Unix
Classifier: Programming Language :: Python :: 2.6
Classifier: Programming Language :: Python :: 2.7
Classifier: Programming Language :: Python :: 2 :: Only
Classifier: Topic :: Games/Entertainment
